[
  {
    "Type": "AnimMontage",
    "Name": "AM_Skill01_Start",
    "Flags": "RF_Public | RF_Transactional | RF_WasLoaded | RF_LoadCompleted",
    "Class": "UScriptClass'AnimMontage'",
    "Package": "Client/Content/Aki/Character/Role/FemaleXL/ChangLi/CommonAnim/AM_Skill01_Start",
    "Properties": {
      "CompositeSections": [
        {
          "SectionName": "Default",
          "NextSectionName": "None",
          "MetaData": [],
          "LinkedMontage": {
            "ObjectName": "AnimMontage'AM_Skill01_Start'",
            "ObjectPath": "Client/Content/Aki/Character/Role/FemaleXL/ChangLi/CommonAnim/AM_Skill01_Start.0"
          },
          "SlotIndex": 0,
          "SegmentIndex": 0,
          "LinkMethod": "EAnimLinkMethod::Absolute",
          "CachedLinkMethod": "EAnimLinkMethod::Absolute",
          "SegmentBeginTime": 0.0,
          "SegmentLength": 1.1666666,
          "LinkValue": 0.0,
          "LinkedSequence": {
            "ObjectName": "AnimSequence'Skill01_Start'",
            "ObjectPath": "Client/Content/Aki/Character/Role/FemaleXL/ChangLi/CommonAnim/Skill01_Start.6"
          }
        }
      ],
      "SlotAnimTracks": [
        {
          "SlotName": "DefaultSlot",
          "AnimTrack": {
            "AnimSegments": [
              {
                "AnimReference": {
                  "ObjectName": "AnimSequence'Skill01_Start'",
                  "ObjectPath": "Client/Content/Aki/Character/Role/FemaleXL/ChangLi/CommonAnim/Skill01_Start.6"
                },
                "StartPos": 0.0,
                "AnimStartTime": 0.0,
                "AnimEndTime": 1.1666666,
                "AnimPlayRate": 1.0,
                "LoopingCount": 1
              }
            ]
          }
        }
      ],
      "Notifies": [
        {
          "TriggerTimeOffset": -0.0001,
          "EndTriggerTimeOffset": 0.0,
          "TriggerWeightThreshold": 1E-05,
          "NotifyName": "TsAnimNotifyStateAddTag_C",
          "Notify": null,
          "NotifyStateClass": {
            "ObjectName": "TsAnimNotifyStateAddTag_C'AM_Skill01_Start:TsAnimNotifyStateAddTag_C_0'",
            "ObjectPath": "Client/Content/Aki/Character/Role/FemaleXL/ChangLi/CommonAnim/AM_Skill01_Start.16"
          },
          "Duration": 0.7837622,
          "EndLink": {
            "LinkedMontage": {
              "ObjectName": "AnimMontage'AM_Skill01_Start'",
              "ObjectPath": "Client/Content/Aki/Character/Role/FemaleXL/ChangLi/CommonAnim/AM_Skill01_Start.0"
            },
            "SlotIndex": 0,
            "SegmentIndex": 0,
            "LinkMethod": "EAnimLinkMethod::Absolute",
            "CachedLinkMethod": "EAnimLinkMethod::Absolute",
            "SegmentBeginTime": 0.0,
            "SegmentLength": 1.1666666,
            "LinkValue": 0.7837622,
            "LinkedSequence": {
              "ObjectName": "AnimSequence'Skill01_Start'",
              "ObjectPath": "Client/Content/Aki/Character/Role/FemaleXL/ChangLi/CommonAnim/Skill01_Start.6"
            }
          },
          "bConvertedFromBranchingPoint": false,
          "MontageTickType": "EMontageNotifyTickType::Queued",
          "bEnabled": true,
          "NotifyTriggerChance": 1.0,
          "NotifyFilterType": "ENotifyFilterType::NoFiltering",
          "NotifyFilterLOD": 0,
          "bTriggerOnDedicatedServer": true,
          "bTriggerOnFollower": false,
          "bForceTriggerOnState": false,
          "TrackIndex": 9,
          "LinkedMontage": {
            "ObjectName": "AnimMontage'AM_Skill01_Start'",
            "ObjectPath": "Client/Content/Aki/Character/Role/FemaleXL/ChangLi/CommonAnim/AM_Skill01_Start.0"
          },
          "SlotIndex": 0,
          "SegmentIndex": 0,
          "LinkMethod": "EAnimLinkMethod::Absolute",
          "CachedLinkMethod": "EAnimLinkMethod::Absolute",
          "SegmentBeginTime": 0.0,
          "SegmentLength": 1.1666666,
          "LinkValue": 0.0,
          "LinkedSequence": {
            "ObjectName": "AnimSequence'Skill01_Start'",
            "ObjectPath": "Client/Content/Aki/Character/Role/FemaleXL/ChangLi/CommonAnim/Skill01_Start.6"
          }
        },
        {
          "TriggerTimeOffset": 0.0001,
          "EndTriggerTimeOffset": -0.0001,
          "TriggerWeightThreshold": 1E-05,
          "NotifyName": "TsAnimNotifyStateGoThrough_C",
          "Notify": null,
          "NotifyStateClass": {
            "ObjectName": "TsAnimNotifyStateGoThrough_C'AM_Skill01_Start:TsAnimNotifyStateGoThrough_C_0'",
            "ObjectPath": "Client/Content/Aki/Character/Role/FemaleXL/ChangLi/CommonAnim/AM_Skill01_Start.19"
          },
          "Duration": 1.1666666,
          "EndLink": {
            "LinkedMontage": {
              "ObjectName": "AnimMontage'AM_Skill01_Start'",
              "ObjectPath": "Client/Content/Aki/Character/Role/FemaleXL/ChangLi/CommonAnim/AM_Skill01_Start.0"
            },
            "SlotIndex": 0,
            "SegmentIndex": 0,
            "LinkMethod": "EAnimLinkMethod::Absolute",
            "CachedLinkMethod": "EAnimLinkMethod::Absolute",
            "SegmentBeginTime": 0.0,
            "SegmentLength": 1.1666666,
            "LinkValue": 1.1666666,
            "LinkedSequence": {
              "ObjectName": "AnimSequence'Skill01_Start'",
              "ObjectPath": "Client/Content/Aki/Character/Role/FemaleXL/ChangLi/CommonAnim/Skill01_Start.6"
            }
          },
          "bConvertedFromBranchingPoint": false,
          "MontageTickType": "EMontageNotifyTickType::Queued",
          "bEnabled": true,
          "NotifyTriggerChance": 1.0,
          "NotifyFilterType": "ENotifyFilterType::NoFiltering",
          "NotifyFilterLOD": 0,
          "bTriggerOnDedicatedServer": true,
          "bTriggerOnFollower": false,
          "bForceTriggerOnState": false,
          "TrackIndex": 1,
          "LinkedMontage": {
            "ObjectName": "AnimMontage'AM_Skill01_Start'",
            "ObjectPath": "Client/Content/Aki/Character/Role/FemaleXL/ChangLi/CommonAnim/AM_Skill01_Start.0"
          },
          "SlotIndex": 0,
          "SegmentIndex": 0,
          "LinkMethod": "EAnimLinkMethod::Absolute",
          "CachedLinkMethod": "EAnimLinkMethod::Absolute",
          "SegmentBeginTime": 0.0,
          "SegmentLength": 1.1666666,
          "LinkValue": 0.0,
          "LinkedSequence": {
            "ObjectName": "AnimSequence'Skill01_Start'",
            "ObjectPath": "Client/Content/Aki/Character/Role/FemaleXL/ChangLi/CommonAnim/Skill01_Start.6"
          }
        },
        {
          "TriggerTimeOffset": 0.0001,
          "EndTriggerTimeOffset": 0.0,
          "TriggerWeightThreshold": 1E-05,
          "NotifyName": "AnimNotifyStateAddMaterialControllerDataGroup_C",
          "Notify": null,
          "NotifyStateClass": {
            "ObjectName": "AnimNotifyStateAddMaterialControllerDataGroup_C'AM_Skill01_Start:AnimNotifyStateAddMaterialControllerDataGroup_C_1'",
            "ObjectPath": "Client/Content/Aki/Character/Role/FemaleXL/ChangLi/CommonAnim/AM_Skill01_Start.2"
          },
          "Duration": 0.771993,
          "EndLink": {
            "LinkedMontage": {
              "ObjectName": "AnimMontage'AM_Skill01_Start'",
              "ObjectPath": "Client/Content/Aki/Character/Role/FemaleXL/ChangLi/CommonAnim/AM_Skill01_Start.0"
            },
            "SlotIndex": 0,
            "SegmentIndex": 0,
            "LinkMethod": "EAnimLinkMethod::Absolute",
            "CachedLinkMethod": "EAnimLinkMethod::Absolute",
            "SegmentBeginTime": 0.0,
            "SegmentLength": 1.1666666,
            "LinkValue": 0.771993,
            "LinkedSequence": {
              "ObjectName": "AnimSequence'Skill01_Start'",
              "ObjectPath": "Client/Content/Aki/Character/Role/FemaleXL/ChangLi/CommonAnim/Skill01_Start.6"
            }
          },
          "bConvertedFromBranchingPoint": false,
          "MontageTickType": "EMontageNotifyTickType::Queued",
          "bEnabled": true,
          "NotifyTriggerChance": 1.0,
          "NotifyFilterType": "ENotifyFilterType::NoFiltering",
          "NotifyFilterLOD": 0,
          "bTriggerOnDedicatedServer": true,
          "bTriggerOnFollower": false,
          "bForceTriggerOnState": false,
          "TrackIndex": 2,
          "LinkedMontage": {
            "ObjectName": "AnimMontage'AM_Skill01_Start'",
            "ObjectPath": "Client/Content/Aki/Character/Role/FemaleXL/ChangLi/CommonAnim/AM_Skill01_Start.0"
          },
          "SlotIndex": 0,
          "SegmentIndex": 0,
          "LinkMethod": "EAnimLinkMethod::Absolute",
          "CachedLinkMethod": "EAnimLinkMethod::Absolute",
          "SegmentBeginTime": 0.0,
          "SegmentLength": 1.1666666,
          "LinkValue": 0.0,
          "LinkedSequence": {
            "ObjectName": "AnimSequence'Skill01_Start'",
            "ObjectPath": "Client/Content/Aki/Character/Role/FemaleXL/ChangLi/CommonAnim/Skill01_Start.6"
          }
        },
        {
          "TriggerTimeOffset": 0.0001,
          "EndTriggerTimeOffset": 0.0,
          "TriggerWeightThreshold": 1E-05,
          "NotifyName": "AnimNotifyStateGhost_C",
          "Notify": null,
          "NotifyStateClass": {
            "ObjectName": "AnimNotifyStateGhost_C'AM_Skill01_Start:AnimNotifyStateGhost_C_0'",
            "ObjectPath": "Client/Content/Aki/Character/Role/FemaleXL/ChangLi/CommonAnim/AM_Skill01_Start.3"
          },
          "Duration": 0.0594219,
          "EndLink": {
            "LinkedMontage": {
              "ObjectName": "AnimMontage'AM_Skill01_Start'",
              "ObjectPath": "Client/Content/Aki/Character/Role/FemaleXL/ChangLi/CommonAnim/AM_Skill01_Start.0"
            },
            "SlotIndex": 0,
            "SegmentIndex": 0,
            "LinkMethod": "EAnimLinkMethod::Absolute",
            "CachedLinkMethod": "EAnimLinkMethod::Absolute",
            "SegmentBeginTime": 0.0,
            "SegmentLength": 1.1666666,
            "LinkValue": 0.0594219,
            "LinkedSequence": {
              "ObjectName": "AnimSequence'Skill01_Start'",
              "ObjectPath": "Client/Content/Aki/Character/Role/FemaleXL/ChangLi/CommonAnim/Skill01_Start.6"
            }
          },
          "bConvertedFromBranchingPoint": false,
          "MontageTickType": "EMontageNotifyTickType::Queued",
          "bEnabled": true,
          "NotifyTriggerChance": 1.0,
          "NotifyFilterType": "ENotifyFilterType::NoFiltering",
          "NotifyFilterLOD": 0,
          "bTriggerOnDedicatedServer": true,
          "bTriggerOnFollower": false,
          "bForceTriggerOnState": false,
          "TrackIndex": 3,
          "LinkedMontage": {
            "ObjectName": "AnimMontage'AM_Skill01_Start'",
            "ObjectPath": "Client/Content/Aki/Character/Role/FemaleXL/ChangLi/CommonAnim/AM_Skill01_Start.0"
          },
          "SlotIndex": 0,
          "SegmentIndex": 0,
          "LinkMethod": "EAnimLinkMethod::Absolute",
          "CachedLinkMethod": "EAnimLinkMethod::Absolute",
          "SegmentBeginTime": 0.0,
          "SegmentLength": 1.1666666,
          "LinkValue": 0.0,
          "LinkedSequence": {
            "ObjectName": "AnimSequence'Skill01_Start'",
            "ObjectPath": "Client/Content/Aki/Character/Role/FemaleXL/ChangLi/CommonAnim/Skill01_Start.6"
          }
        },
        {
          "TriggerTimeOffset": 0.0001,
          "EndTriggerTimeOffset": 0.0,
          "TriggerWeightThreshold": 1E-05,
          "NotifyName": "TsAnimNotifyStateAddTag_C",
          "Notify": null,
          "NotifyStateClass": {
            "ObjectName": "TsAnimNotifyStateAddTag_C'AM_Skill01_Start:TsAnimNotifyStateAddTag_C_2'",
            "ObjectPath": "Client/Content/Aki/Character/Role/FemaleXL/ChangLi/CommonAnim/AM_Skill01_Start.18"
          },
          "Duration": 0.7713279,
          "EndLink": {
            "LinkedMontage": {
              "ObjectName": "AnimMontage'AM_Skill01_Start'",
              "ObjectPath": "Client/Content/Aki/Character/Role/FemaleXL/ChangLi/CommonAnim/AM_Skill01_Start.0"
            },
            "SlotIndex": 0,
            "SegmentIndex": 0,
            "LinkMethod": "EAnimLinkMethod::Absolute",
            "CachedLinkMethod": "EAnimLinkMethod::Absolute",
            "SegmentBeginTime": 0.0,
            "SegmentLength": 1.1666666,
            "LinkValue": 0.7713279,
            "LinkedSequence": {
              "ObjectName": "AnimSequence'Skill01_Start'",
              "ObjectPath": "Client/Content/Aki/Character/Role/FemaleXL/ChangLi/CommonAnim/Skill01_Start.6"
            }
          },
          "bConvertedFromBranchingPoint": false,
          "MontageTickType": "EMontageNotifyTickType::Queued",
          "bEnabled": true,
          "NotifyTriggerChance": 1.0,
          "NotifyFilterType": "ENotifyFilterType::NoFiltering",
          "NotifyFilterLOD": 0,
          "bTriggerOnDedicatedServer": true,
          "bTriggerOnFollower": false,
          "bForceTriggerOnState": false,
          "TrackIndex": 4,
          "LinkedMontage": {
            "ObjectName": "AnimMontage'AM_Skill01_Start'",
            "ObjectPath": "Client/Content/Aki/Character/Role/FemaleXL/ChangLi/CommonAnim/AM_Skill01_Start.0"
          },
          "SlotIndex": 0,
          "SegmentIndex": 0,
          "LinkMethod": "EAnimLinkMethod::Absolute",
          "CachedLinkMethod": "EAnimLinkMethod::Absolute",
          "SegmentBeginTime": 0.0,
          "SegmentLength": 1.1666666,
          "LinkValue": 0.0,
          "LinkedSequence": {
            "ObjectName": "AnimSequence'Skill01_Start'",
            "ObjectPath": "Client/Content/Aki/Character/Role/FemaleXL/ChangLi/CommonAnim/Skill01_Start.6"
          }
        },
        {
          "TriggerTimeOffset": 0.0001,
          "EndTriggerTimeOffset": 0.0001,
          "TriggerWeightThreshold": 1E-05,
          "NotifyName": "TsAnimNotifyChangeSkillPriority_C",
          "Notify": {
            "ObjectName": "TsAnimNotifyChangeSkillPriority_C'AM_Skill01_Start:TsAnimNotifyChangeSkillPriority_C_0'",
            "ObjectPath": "Client/Content/Aki/Character/Role/FemaleXL/ChangLi/CommonAnim/AM_Skill01_Start.12"
          },
          "NotifyStateClass": null,
          "Duration": 0.0,
          "EndLink": {
            "LinkedMontage": null,
            "SlotIndex": 0,
            "SegmentIndex": -1,
            "LinkMethod": "EAnimLinkMethod::Absolute",
            "CachedLinkMethod": "EAnimLinkMethod::Absolute",
            "SegmentBeginTime": 0.0,
            "SegmentLength": 0.0,
            "LinkValue": 0.0,
            "LinkedSequence": null
          },
          "bConvertedFromBranchingPoint": false,
          "MontageTickType": "EMontageNotifyTickType::Queued",
          "bEnabled": true,
          "NotifyTriggerChance": 1.0,
          "NotifyFilterType": "ENotifyFilterType::NoFiltering",
          "NotifyFilterLOD": 0,
          "bTriggerOnDedicatedServer": true,
          "bTriggerOnFollower": false,
          "bForceTriggerOnState": false,
          "TrackIndex": 6,
          "LinkedMontage": {
            "ObjectName": "AnimMontage'AM_Skill01_Start'",
            "ObjectPath": "Client/Content/Aki/Character/Role/FemaleXL/ChangLi/CommonAnim/AM_Skill01_Start.0"
          },
          "SlotIndex": 0,
          "SegmentIndex": 0,
          "LinkMethod": "EAnimLinkMethod::Absolute",
          "CachedLinkMethod": "EAnimLinkMethod::Absolute",
          "SegmentBeginTime": 0.0,
          "SegmentLength": 1.1666666,
          "LinkValue": 0.0,
          "LinkedSequence": {
            "ObjectName": "AnimSequence'Skill01_Start'",
            "ObjectPath": "Client/Content/Aki/Character/Role/FemaleXL/ChangLi/CommonAnim/Skill01_Start.6"
          }
        },
        {
          "TriggerTimeOffset": 0.0001,
          "EndTriggerTimeOffset": 0.0,
          "TriggerWeightThreshold": 1E-05,
          "NotifyName": "TsAnimNotifyStateAddTag_C",
          "Notify": null,
          "NotifyStateClass": {
            "ObjectName": "TsAnimNotifyStateAddTag_C'AM_Skill01_Start:TsAnimNotifyStateAddTag_C_1'",
            "ObjectPath": "Client/Content/Aki/Character/Role/FemaleXL/ChangLi/CommonAnim/AM_Skill01_Start.17"
          },
          "Duration": 0.80348533,
          "EndLink": {
            "LinkedMontage": {
              "ObjectName": "AnimMontage'AM_Skill01_Start'",
              "ObjectPath": "Client/Content/Aki/Character/Role/FemaleXL/ChangLi/CommonAnim/AM_Skill01_Start.0"
            },
            "SlotIndex": 0,
            "SegmentIndex": 0,
            "LinkMethod": "EAnimLinkMethod::Absolute",
            "CachedLinkMethod": "EAnimLinkMethod::Absolute",
            "SegmentBeginTime": 0.0,
            "SegmentLength": 1.1666666,
            "LinkValue": 0.80348533,
            "LinkedSequence": {
              "ObjectName": "AnimSequence'Skill01_Start'",
              "ObjectPath": "Client/Content/Aki/Character/Role/FemaleXL/ChangLi/CommonAnim/Skill01_Start.6"
            }
          },
          "bConvertedFromBranchingPoint": false,
          "MontageTickType": "EMontageNotifyTickType::Queued",
          "bEnabled": true,
          "NotifyTriggerChance": 1.0,
          "NotifyFilterType": "ENotifyFilterType::NoFiltering",
          "NotifyFilterLOD": 0,
          "bTriggerOnDedicatedServer": true,
          "bTriggerOnFollower": false,
          "bForceTriggerOnState": false,
          "TrackIndex": 7,
          "LinkedMontage": {
            "ObjectName": "AnimMontage'AM_Skill01_Start'",
            "ObjectPath": "Client/Content/Aki/Character/Role/FemaleXL/ChangLi/CommonAnim/AM_Skill01_Start.0"
          },
          "SlotIndex": 0,
          "SegmentIndex": 0,
          "LinkMethod": "EAnimLinkMethod::Absolute",
          "CachedLinkMethod": "EAnimLinkMethod::Absolute",
          "SegmentBeginTime": 0.0,
          "SegmentLength": 1.1666666,
          "LinkValue": 0.0,
          "LinkedSequence": {
            "ObjectName": "AnimSequence'Skill01_Start'",
            "ObjectPath": "Client/Content/Aki/Character/Role/FemaleXL/ChangLi/CommonAnim/Skill01_Start.6"
          }
        },
        {
          "TriggerTimeOffset": 0.0001,
          "EndTriggerTimeOffset": 0.0,
          "TriggerWeightThreshold": 1E-05,
          "NotifyName": "TsAnimNotifyStatePositionBranchTarget_C",
          "Notify": null,
          "NotifyStateClass": {
            "ObjectName": "TsAnimNotifyStatePositionBranchTarget_C'AM_Skill01_Start:TsAnimNotifyStatePositionBranchTarget_C_1'",
            "ObjectPath": "Client/Content/Aki/Character/Role/FemaleXL/ChangLi/CommonAnim/AM_Skill01_Start.20"
          },
          "Duration": 0.14676514,
          "EndLink": {
            "LinkedMontage": {
              "ObjectName": "AnimMontage'AM_Skill01_Start'",
              "ObjectPath": "Client/Content/Aki/Character/Role/FemaleXL/ChangLi/CommonAnim/AM_Skill01_Start.0"
            },
            "SlotIndex": 0,
            "SegmentIndex": 0,
            "LinkMethod": "EAnimLinkMethod::Absolute",
            "CachedLinkMethod": "EAnimLinkMethod::Absolute",
            "SegmentBeginTime": 0.0,
            "SegmentLength": 1.1666666,
            "LinkValue": 0.14676514,
            "LinkedSequence": {
              "ObjectName": "AnimSequence'Skill01_Start'",
              "ObjectPath": "Client/Content/Aki/Character/Role/FemaleXL/ChangLi/CommonAnim/Skill01_Start.6"
            }
          },
          "bConvertedFromBranchingPoint": false,
          "MontageTickType": "EMontageNotifyTickType::Queued",
          "bEnabled": true,
          "NotifyTriggerChance": 1.0,
          "NotifyFilterType": "ENotifyFilterType::NoFiltering",
          "NotifyFilterLOD": 0,
          "bTriggerOnDedicatedServer": true,
          "bTriggerOnFollower": false,
          "bForceTriggerOnState": false,
          "TrackIndex": 8,
          "LinkedMontage": {
            "ObjectName": "AnimMontage'AM_Skill01_Start'",
            "ObjectPath": "Client/Content/Aki/Character/Role/FemaleXL/ChangLi/CommonAnim/AM_Skill01_Start.0"
          },
          "SlotIndex": 0,
          "SegmentIndex": 0,
          "LinkMethod": "EAnimLinkMethod::Absolute",
          "CachedLinkMethod": "EAnimLinkMethod::Absolute",
          "SegmentBeginTime": 0.0,
          "SegmentLength": 1.1666666,
          "LinkValue": 0.0,
          "LinkedSequence": {
            "ObjectName": "AnimSequence'Skill01_Start'",
            "ObjectPath": "Client/Content/Aki/Character/Role/FemaleXL/ChangLi/CommonAnim/Skill01_Start.6"
          }
        },
        {
          "TriggerTimeOffset": 0.0001,
          "EndTriggerTimeOffset": 0.0001,
          "TriggerWeightThreshold": 1E-05,
          "NotifyName": "TsAnimNotifyWeaponHide_C",
          "Notify": {
            "ObjectName": "TsAnimNotifyWeaponHide_C'AM_Skill01_Start:TsAnimNotifyWeaponHide_C_1'",
            "ObjectPath": "Client/Content/Aki/Character/Role/FemaleXL/ChangLi/CommonAnim/AM_Skill01_Start.21"
          },
          "NotifyStateClass": null,
          "Duration": 0.0,
          "EndLink": {
            "LinkedMontage": null,
            "SlotIndex": 0,
            "SegmentIndex": -1,
            "LinkMethod": "EAnimLinkMethod::Absolute",
            "CachedLinkMethod": "EAnimLinkMethod::Absolute",
            "SegmentBeginTime": 0.0,
            "SegmentLength": 0.0,
            "LinkValue": 0.0,
            "LinkedSequence": null
          },
          "bConvertedFromBranchingPoint": false,
          "MontageTickType": "EMontageNotifyTickType::Queued",
          "bEnabled": true,
          "NotifyTriggerChance": 1.0,
          "NotifyFilterType": "ENotifyFilterType::NoFiltering",
          "NotifyFilterLOD": 0,
          "bTriggerOnDedicatedServer": true,
          "bTriggerOnFollower": false,
          "bForceTriggerOnState": false,
          "TrackIndex": 10,
          "LinkedMontage": {
            "ObjectName": "AnimMontage'AM_Skill01_Start'",
            "ObjectPath": "Client/Content/Aki/Character/Role/FemaleXL/ChangLi/CommonAnim/AM_Skill01_Start.0"
          },
          "SlotIndex": 0,
          "SegmentIndex": 0,
          "LinkMethod": "EAnimLinkMethod::Absolute",
          "CachedLinkMethod": "EAnimLinkMethod::Absolute",
          "SegmentBeginTime": 0.0,
          "SegmentLength": 1.1666666,
          "LinkValue": 0.0,
          "LinkedSequence": {
            "ObjectName": "AnimSequence'Skill01_Start'",
            "ObjectPath": "Client/Content/Aki/Character/Role/FemaleXL/ChangLi/CommonAnim/Skill01_Start.6"
          }
        },
        {
          "TriggerTimeOffset": 0.0001,
          "EndTriggerTimeOffset": -0.0001,
          "TriggerWeightThreshold": 1E-05,
          "NotifyName": "TsAnimNotifyStateAddBuff_C",
          "Notify": null,
          "NotifyStateClass": {
            "ObjectName": "TsAnimNotifyStateAddBuff_C'AM_Skill01_Start:TsAnimNotifyStateAddBuff_C_0'",
            "ObjectPath": "Client/Content/Aki/Character/Role/FemaleXL/ChangLi/CommonAnim/AM_Skill01_Start.14"
          },
          "Duration": 1.1666666,
          "EndLink": {
            "LinkedMontage": {
              "ObjectName": "AnimMontage'AM_Skill01_Start'",
              "ObjectPath": "Client/Content/Aki/Character/Role/FemaleXL/ChangLi/CommonAnim/AM_Skill01_Start.0"
            },
            "SlotIndex": 0,
            "SegmentIndex": 0,
            "LinkMethod": "EAnimLinkMethod::Absolute",
            "CachedLinkMethod": "EAnimLinkMethod::Absolute",
            "SegmentBeginTime": 0.0,
            "SegmentLength": 1.1666666,
            "LinkValue": 1.1666666,
            "LinkedSequence": {
              "ObjectName": "AnimSequence'Skill01_Start'",
              "ObjectPath": "Client/Content/Aki/Character/Role/FemaleXL/ChangLi/CommonAnim/Skill01_Start.6"
            }
          },
          "bConvertedFromBranchingPoint": false,
          "MontageTickType": "EMontageNotifyTickType::Queued",
          "bEnabled": true,
          "NotifyTriggerChance": 1.0,
          "NotifyFilterType": "ENotifyFilterType::NoFiltering",
          "NotifyFilterLOD": 0,
          "bTriggerOnDedicatedServer": true,
          "bTriggerOnFollower": false,
          "bForceTriggerOnState": false,
          "TrackIndex": 11,
          "LinkedMontage": {
            "ObjectName": "AnimMontage'AM_Skill01_Start'",
            "ObjectPath": "Client/Content/Aki/Character/Role/FemaleXL/ChangLi/CommonAnim/AM_Skill01_Start.0"
          },
          "SlotIndex": 0,
          "SegmentIndex": 0,
          "LinkMethod": "EAnimLinkMethod::Absolute",
          "CachedLinkMethod": "EAnimLinkMethod::Absolute",
          "SegmentBeginTime": 0.0,
          "SegmentLength": 1.1666666,
          "LinkValue": 0.0,
          "LinkedSequence": {
            "ObjectName": "AnimSequence'Skill01_Start'",
            "ObjectPath": "Client/Content/Aki/Character/Role/FemaleXL/ChangLi/CommonAnim/Skill01_Start.6"
          }
        },
        {
          "TriggerTimeOffset": 0.0001,
          "EndTriggerTimeOffset": -0.0001,
          "TriggerWeightThreshold": 1E-05,
          "NotifyName": "TsAnimNotifyStateAddBuff_C",
          "Notify": null,
          "NotifyStateClass": {
            "ObjectName": "TsAnimNotifyStateAddBuff_C'AM_Skill01_Start:TsAnimNotifyStateAddBuff_C_1'",
            "ObjectPath": "Client/Content/Aki/Character/Role/FemaleXL/ChangLi/CommonAnim/AM_Skill01_Start.15"
          },
          "Duration": 1.1666666,
          "EndLink": {
            "LinkedMontage": {
              "ObjectName": "AnimMontage'AM_Skill01_Start'",
              "ObjectPath": "Client/Content/Aki/Character/Role/FemaleXL/ChangLi/CommonAnim/AM_Skill01_Start.0"
            },
            "SlotIndex": 0,
            "SegmentIndex": 0,
            "LinkMethod": "EAnimLinkMethod::Absolute",
            "CachedLinkMethod": "EAnimLinkMethod::Absolute",
            "SegmentBeginTime": 0.0,
            "SegmentLength": 1.1666666,
            "LinkValue": 1.1666666,
            "LinkedSequence": {
              "ObjectName": "AnimSequence'Skill01_Start'",
              "ObjectPath": "Client/Content/Aki/Character/Role/FemaleXL/ChangLi/CommonAnim/Skill01_Start.6"
            }
          },
          "bConvertedFromBranchingPoint": false,
          "MontageTickType": "EMontageNotifyTickType::Queued",
          "bEnabled": true,
          "NotifyTriggerChance": 1.0,
          "NotifyFilterType": "ENotifyFilterType::NoFiltering",
          "NotifyFilterLOD": 0,
          "bTriggerOnDedicatedServer": true,
          "bTriggerOnFollower": false,
          "bForceTriggerOnState": false,
          "TrackIndex": 12,
          "LinkedMontage": {
            "ObjectName": "AnimMontage'AM_Skill01_Start'",
            "ObjectPath": "Client/Content/Aki/Character/Role/FemaleXL/ChangLi/CommonAnim/AM_Skill01_Start.0"
          },
          "SlotIndex": 0,
          "SegmentIndex": 0,
          "LinkMethod": "EAnimLinkMethod::Absolute",
          "CachedLinkMethod": "EAnimLinkMethod::Absolute",
          "SegmentBeginTime": 0.0,
          "SegmentLength": 1.1666666,
          "LinkValue": 0.0,
          "LinkedSequence": {
            "ObjectName": "AnimSequence'Skill01_Start'",
            "ObjectPath": "Client/Content/Aki/Character/Role/FemaleXL/ChangLi/CommonAnim/Skill01_Start.6"
          }
        },
        {
          "TriggerTimeOffset": 0.0,
          "EndTriggerTimeOffset": 0.0001,
          "TriggerWeightThreshold": 1E-05,
          "NotifyName": "TsAnimNotifyAudioEvent_C",
          "Notify": {
            "ObjectName": "TsAnimNotifyAudioEvent_C'AM_Skill01_Start:TsAnimNotifyAudioEvent_C_0'",
            "ObjectPath": "Client/Content/Aki/Character/Role/FemaleXL/ChangLi/CommonAnim/AM_Skill01_Start.10"
          },
          "NotifyStateClass": null,
          "Duration": 0.0,
          "EndLink": {
            "LinkedMontage": null,
            "SlotIndex": 0,
            "SegmentIndex": -1,
            "LinkMethod": "EAnimLinkMethod::Absolute",
            "CachedLinkMethod": "EAnimLinkMethod::Absolute",
            "SegmentBeginTime": 0.0,
            "SegmentLength": 0.0,
            "LinkValue": 0.0,
            "LinkedSequence": null
          },
          "bConvertedFromBranchingPoint": false,
          "MontageTickType": "EMontageNotifyTickType::Queued",
          "bEnabled": true,
          "NotifyTriggerChance": 1.0,
          "NotifyFilterType": "ENotifyFilterType::NoFiltering",
          "NotifyFilterLOD": 0,
          "bTriggerOnDedicatedServer": true,
          "bTriggerOnFollower": false,
          "bForceTriggerOnState": false,
          "TrackIndex": 13,
          "LinkedMontage": {
            "ObjectName": "AnimMontage'AM_Skill01_Start'",
            "ObjectPath": "Client/Content/Aki/Character/Role/FemaleXL/ChangLi/CommonAnim/AM_Skill01_Start.0"
          },
          "SlotIndex": 0,
          "SegmentIndex": 0,
          "LinkMethod": "EAnimLinkMethod::Absolute",
          "CachedLinkMethod": "EAnimLinkMethod::Absolute",
          "SegmentBeginTime": 0.0,
          "SegmentLength": 1.1666666,
          "LinkValue": 0.014822084,
          "LinkedSequence": {
            "ObjectName": "AnimSequence'Skill01_Start'",
            "ObjectPath": "Client/Content/Aki/Character/Role/FemaleXL/ChangLi/CommonAnim/Skill01_Start.6"
          }
        },
        {
          "TriggerTimeOffset": 0.0,
          "EndTriggerTimeOffset": 0.0,
          "TriggerWeightThreshold": 1E-05,
          "NotifyName": "TsAnimNotifyCameraModify_C",
          "Notify": {
            "ObjectName": "TsAnimNotifyCameraModify_C'AM_Skill01_Start:TsAnimNotifyCameraModify_C_0'",
            "ObjectPath": "Client/Content/Aki/Character/Role/FemaleXL/ChangLi/CommonAnim/AM_Skill01_Start.11"
          },
          "NotifyStateClass": null,
          "Duration": 0.0,
          "EndLink": {
            "LinkedMontage": null,
            "SlotIndex": 0,
            "SegmentIndex": -1,
            "LinkMethod": "EAnimLinkMethod::Absolute",
            "CachedLinkMethod": "EAnimLinkMethod::Absolute",
            "SegmentBeginTime": 0.0,
            "SegmentLength": 0.0,
            "LinkValue": 0.026010629,
            "LinkedSequence": null
          },
          "bConvertedFromBranchingPoint": false,
          "MontageTickType": "EMontageNotifyTickType::Queued",
          "bEnabled": true,
          "NotifyTriggerChance": 1.0,
          "NotifyFilterType": "ENotifyFilterType::NoFiltering",
          "NotifyFilterLOD": 0,
          "bTriggerOnDedicatedServer": true,
          "bTriggerOnFollower": false,
          "bForceTriggerOnState": false,
          "TrackIndex": 0,
          "LinkedMontage": {
            "ObjectName": "AnimMontage'AM_Skill01_Start'",
            "ObjectPath": "Client/Content/Aki/Character/Role/FemaleXL/ChangLi/CommonAnim/AM_Skill01_Start.0"
          },
          "SlotIndex": 0,
          "SegmentIndex": 0,
          "LinkMethod": "EAnimLinkMethod::Absolute",
          "CachedLinkMethod": "EAnimLinkMethod::Absolute",
          "SegmentBeginTime": 0.0,
          "SegmentLength": 1.1666666,
          "LinkValue": 0.026010629,
          "LinkedSequence": {
            "ObjectName": "AnimSequence'Skill01_Start'",
            "ObjectPath": "Client/Content/Aki/Character/Role/FemaleXL/ChangLi/CommonAnim/Skill01_Start.6"
          }
        },
        {
          "TriggerTimeOffset": 0.0,
          "EndTriggerTimeOffset": 0.0,
          "TriggerWeightThreshold": 1E-05,
          "NotifyName": "AnimNotifyStateGhost_C",
          "Notify": null,
          "NotifyStateClass": {
            "ObjectName": "AnimNotifyStateGhost_C'AM_Skill01_Start:AnimNotifyStateGhost_C_1'",
            "ObjectPath": "Client/Content/Aki/Character/Role/FemaleXL/ChangLi/CommonAnim/AM_Skill01_Start.4"
          },
          "Duration": 0.034750566,
          "EndLink": {
            "LinkedMontage": {
              "ObjectName": "AnimMontage'AM_Skill01_Start'",
              "ObjectPath": "Client/Content/Aki/Character/Role/FemaleXL/ChangLi/CommonAnim/AM_Skill01_Start.0"
            },
            "SlotIndex": 0,
            "SegmentIndex": 0,
            "LinkMethod": "EAnimLinkMethod::Absolute",
            "CachedLinkMethod": "EAnimLinkMethod::Absolute",
            "SegmentBeginTime": 0.0,
            "SegmentLength": 1.1666666,
            "LinkValue": 0.1552783,
            "LinkedSequence": {
              "ObjectName": "AnimSequence'Skill01_Start'",
              "ObjectPath": "Client/Content/Aki/Character/Role/FemaleXL/ChangLi/CommonAnim/Skill01_Start.6"
            }
          },
          "bConvertedFromBranchingPoint": false,
          "MontageTickType": "EMontageNotifyTickType::Queued",
          "bEnabled": true,
          "NotifyTriggerChance": 1.0,
          "NotifyFilterType": "ENotifyFilterType::NoFiltering",
          "NotifyFilterLOD": 0,
          "bTriggerOnDedicatedServer": true,
          "bTriggerOnFollower": false,
          "bForceTriggerOnState": false,
          "TrackIndex": 5,
          "LinkedMontage": {
            "ObjectName": "AnimMontage'AM_Skill01_Start'",
            "ObjectPath": "Client/Content/Aki/Character/Role/FemaleXL/ChangLi/CommonAnim/AM_Skill01_Start.0"
          },
          "SlotIndex": 0,
          "SegmentIndex": 0,
          "LinkMethod": "EAnimLinkMethod::Absolute",
          "CachedLinkMethod": "EAnimLinkMethod::Absolute",
          "SegmentBeginTime": 0.0,
          "SegmentLength": 1.1666666,
          "LinkValue": 0.12052773,
          "LinkedSequence": {
            "ObjectName": "AnimSequence'Skill01_Start'",
            "ObjectPath": "Client/Content/Aki/Character/Role/FemaleXL/ChangLi/CommonAnim/Skill01_Start.6"
          }
        },
        {
          "TriggerTimeOffset": 0.0,
          "EndTriggerTimeOffset": 0.0,
          "TriggerWeightThreshold": 1E-05,
          "NotifyName": "TsAnimNotifyReSkillEvent_C",
          "Notify": {
            "ObjectName": "TsAnimNotifyReSkillEvent_C'AM_Skill01_Start:TsAnimNotifyReSkillEvent_C_0'",
            "ObjectPath": "Client/Content/Aki/Character/Role/FemaleXL/ChangLi/CommonAnim/AM_Skill01_Start.13"
          },
          "NotifyStateClass": null,
          "Duration": 0.0,
          "EndLink": {
            "LinkedMontage": null,
            "SlotIndex": 0,
            "SegmentIndex": -1,
            "LinkMethod": "EAnimLinkMethod::Absolute",
            "CachedLinkMethod": "EAnimLinkMethod::Absolute",
            "SegmentBeginTime": 0.0,
            "SegmentLength": 0.0,
            "LinkValue": 0.16666666,
            "LinkedSequence": null
          },
          "bConvertedFromBranchingPoint": false,
          "MontageTickType": "EMontageNotifyTickType::Queued",
          "bEnabled": true,
          "NotifyTriggerChance": 1.0,
          "NotifyFilterType": "ENotifyFilterType::NoFiltering",
          "NotifyFilterLOD": 0,
          "bTriggerOnDedicatedServer": true,
          "bTriggerOnFollower": false,
          "bForceTriggerOnState": false,
          "TrackIndex": 6,
          "LinkedMontage": {
            "ObjectName": "AnimMontage'AM_Skill01_Start'",
            "ObjectPath": "Client/Content/Aki/Character/Role/FemaleXL/ChangLi/CommonAnim/AM_Skill01_Start.0"
          },
          "SlotIndex": 0,
          "SegmentIndex": 0,
          "LinkMethod": "EAnimLinkMethod::Absolute",
          "CachedLinkMethod": "EAnimLinkMethod::Absolute",
          "SegmentBeginTime": 0.0,
          "SegmentLength": 1.1666666,
          "LinkValue": 0.16666666,
          "LinkedSequence": {
            "ObjectName": "AnimSequence'Skill01_Start'",
            "ObjectPath": "Client/Content/Aki/Character/Role/FemaleXL/ChangLi/CommonAnim/Skill01_Start.6"
          }
        },
        {
          "TriggerTimeOffset": 0.0,
          "EndTriggerTimeOffset": 0.0,
          "TriggerWeightThreshold": 1E-05,
          "NotifyName": "AnimNotifyStateGhost_C",
          "Notify": null,
          "NotifyStateClass": {
            "ObjectName": "AnimNotifyStateGhost_C'AM_Skill01_Start:AnimNotifyStateGhost_C_2'",
            "ObjectPath": "Client/Content/Aki/Character/Role/FemaleXL/ChangLi/CommonAnim/AM_Skill01_Start.5"
          },
          "Duration": 0.033333335,
          "EndLink": {
            "LinkedMontage": {
              "ObjectName": "AnimMontage'AM_Skill01_Start'",
              "ObjectPath": "Client/Content/Aki/Character/Role/FemaleXL/ChangLi/CommonAnim/AM_Skill01_Start.0"
            },
            "SlotIndex": 0,
            "SegmentIndex": 0,
            "LinkMethod": "EAnimLinkMethod::Absolute",
            "CachedLinkMethod": "EAnimLinkMethod::Absolute",
            "SegmentBeginTime": 0.0,
            "SegmentLength": 1.1666666,
            "LinkValue": 0.31680527,
            "LinkedSequence": {
              "ObjectName": "AnimSequence'Skill01_Start'",
              "ObjectPath": "Client/Content/Aki/Character/Role/FemaleXL/ChangLi/CommonAnim/Skill01_Start.6"
            }
          },
          "bConvertedFromBranchingPoint": false,
          "MontageTickType": "EMontageNotifyTickType::Queued",
          "bEnabled": true,
          "NotifyTriggerChance": 1.0,
          "NotifyFilterType": "ENotifyFilterType::NoFiltering",
          "NotifyFilterLOD": 0,
          "bTriggerOnDedicatedServer": true,
          "bTriggerOnFollower": false,
          "bForceTriggerOnState": false,
          "TrackIndex": 5,
          "LinkedMontage": {
            "ObjectName": "AnimMontage'AM_Skill01_Start'",
            "ObjectPath": "Client/Content/Aki/Character/Role/FemaleXL/ChangLi/CommonAnim/AM_Skill01_Start.0"
          },
          "SlotIndex": 0,
          "SegmentIndex": 0,
          "LinkMethod": "EAnimLinkMethod::Absolute",
          "CachedLinkMethod": "EAnimLinkMethod::Absolute",
          "SegmentBeginTime": 0.0,
          "SegmentLength": 1.1666666,
          "LinkValue": 0.28347194,
          "LinkedSequence": {
            "ObjectName": "AnimSequence'Skill01_Start'",
            "ObjectPath": "Client/Content/Aki/Character/Role/FemaleXL/ChangLi/CommonAnim/Skill01_Start.6"
          }
        },
        {
          "TriggerTimeOffset": 0.0,
          "EndTriggerTimeOffset": 0.0,
          "TriggerWeightThreshold": 1E-05,
          "NotifyName": "AnimNotifyStateGhost_C",
          "Notify": null,
          "NotifyStateClass": {
            "ObjectName": "AnimNotifyStateGhost_C'AM_Skill01_Start:AnimNotifyStateGhost_C_3'",
            "ObjectPath": "Client/Content/Aki/Character/Role/FemaleXL/ChangLi/CommonAnim/AM_Skill01_Start.6"
          },
          "Duration": 0.21827501,
          "EndLink": {
            "LinkedMontage": {
              "ObjectName": "AnimMontage'AM_Skill01_Start'",
              "ObjectPath": "Client/Content/Aki/Character/Role/FemaleXL/ChangLi/CommonAnim/AM_Skill01_Start.0"
            },
            "SlotIndex": 0,
            "SegmentIndex": 0,
            "LinkMethod": "EAnimLinkMethod::Absolute",
            "CachedLinkMethod": "EAnimLinkMethod::Absolute",
            "SegmentBeginTime": 0.0,
            "SegmentLength": 1.1666666,
            "LinkValue": 0.73965585,
            "LinkedSequence": {
              "ObjectName": "AnimSequence'Skill01_Start'",
              "ObjectPath": "Client/Content/Aki/Character/Role/FemaleXL/ChangLi/CommonAnim/Skill01_Start.6"
            }
          },
          "bConvertedFromBranchingPoint": false,
          "MontageTickType": "EMontageNotifyTickType::Queued",
          "bEnabled": true,
          "NotifyTriggerChance": 1.0,
          "NotifyFilterType": "ENotifyFilterType::NoFiltering",
          "NotifyFilterLOD": 0,
          "bTriggerOnDedicatedServer": true,
          "bTriggerOnFollower": false,
          "bForceTriggerOnState": false,
          "TrackIndex": 5,
          "LinkedMontage": {
            "ObjectName": "AnimMontage'AM_Skill01_Start'",
            "ObjectPath": "Client/Content/Aki/Character/Role/FemaleXL/ChangLi/CommonAnim/AM_Skill01_Start.0"
          },
          "SlotIndex": 0,
          "SegmentIndex": 0,
          "LinkMethod": "EAnimLinkMethod::Absolute",
          "CachedLinkMethod": "EAnimLinkMethod::Absolute",
          "SegmentBeginTime": 0.0,
          "SegmentLength": 1.1666666,
          "LinkValue": 0.52138084,
          "LinkedSequence": {
            "ObjectName": "AnimSequence'Skill01_Start'",
            "ObjectPath": "Client/Content/Aki/Character/Role/FemaleXL/ChangLi/CommonAnim/Skill01_Start.6"
          }
        },
        {
          "TriggerTimeOffset": 0.0,
          "EndTriggerTimeOffset": 0.0,
          "TriggerWeightThreshold": 1E-05,
          "NotifyName": "AnimNotifyStateAddMaterialControllerDataGroup_C",
          "Notify": null,
          "NotifyStateClass": {
            "ObjectName": "AnimNotifyStateAddMaterialControllerDataGroup_C'AM_Skill01_Start:AnimNotifyStateAddMaterialControllerDataGroup_C_0'",
            "ObjectPath": "Client/Content/Aki/Character/Role/FemaleXL/ChangLi/CommonAnim/AM_Skill01_Start.1"
          },
          "Duration": 0.18277514,
          "EndLink": {
            "LinkedMontage": {
              "ObjectName": "AnimMontage'AM_Skill01_Start'",
              "ObjectPath": "Client/Content/Aki/Character/Role/FemaleXL/ChangLi/CommonAnim/AM_Skill01_Start.0"
            },
            "SlotIndex": 0,
            "SegmentIndex": 0,
            "LinkMethod": "EAnimLinkMethod::Absolute",
            "CachedLinkMethod": "EAnimLinkMethod::Absolute",
            "SegmentBeginTime": 0.0,
            "SegmentLength": 1.1666666,
            "LinkValue": 0.93398,
            "LinkedSequence": {
              "ObjectName": "AnimSequence'Skill01_Start'",
              "ObjectPath": "Client/Content/Aki/Character/Role/FemaleXL/ChangLi/CommonAnim/Skill01_Start.6"
            }
          },
          "bConvertedFromBranchingPoint": false,
          "MontageTickType": "EMontageNotifyTickType::Queued",
          "bEnabled": true,
          "NotifyTriggerChance": 1.0,
          "NotifyFilterType": "ENotifyFilterType::NoFiltering",
          "NotifyFilterLOD": 0,
          "bTriggerOnDedicatedServer": true,
          "bTriggerOnFollower": false,
          "bForceTriggerOnState": false,
          "TrackIndex": 0,
          "LinkedMontage": {
            "ObjectName": "AnimMontage'AM_Skill01_Start'",
            "ObjectPath": "Client/Content/Aki/Character/Role/FemaleXL/ChangLi/CommonAnim/AM_Skill01_Start.0"
          },
          "SlotIndex": 0,
          "SegmentIndex": 0,
          "LinkMethod": "EAnimLinkMethod::Absolute",
          "CachedLinkMethod": "EAnimLinkMethod::Absolute",
          "SegmentBeginTime": 0.0,
          "SegmentLength": 1.1666666,
          "LinkValue": 0.75120485,
          "LinkedSequence": {
            "ObjectName": "AnimSequence'Skill01_Start'",
            "ObjectPath": "Client/Content/Aki/Character/Role/FemaleXL/ChangLi/CommonAnim/Skill01_Start.6"
          }
        },
        {
          "TriggerTimeOffset": 0.0,
          "EndTriggerTimeOffset": 0.0001,
          "TriggerWeightThreshold": 1E-05,
          "NotifyName": "TsAnimNotifyAddBuff_C",
          "Notify": {
            "ObjectName": "TsAnimNotifyAddBuff_C'AM_Skill01_Start:TsAnimNotifyAddBuff_C_0'",
            "ObjectPath": "Client/Content/Aki/Character/Role/FemaleXL/ChangLi/CommonAnim/AM_Skill01_Start.7"
          },
          "NotifyStateClass": null,
          "Duration": 0.0,
          "EndLink": {
            "LinkedMontage": null,
            "SlotIndex": 0,
            "SegmentIndex": -1,
            "LinkMethod": "EAnimLinkMethod::Absolute",
            "CachedLinkMethod": "EAnimLinkMethod::Absolute",
            "SegmentBeginTime": 0.0,
            "SegmentLength": 0.0,
            "LinkValue": 0.0,
            "LinkedSequence": null
          },
          "bConvertedFromBranchingPoint": false,
          "MontageTickType": "EMontageNotifyTickType::Queued",
          "bEnabled": true,
          "NotifyTriggerChance": 1.0,
          "NotifyFilterType": "ENotifyFilterType::NoFiltering",
          "NotifyFilterLOD": 0,
          "bTriggerOnDedicatedServer": true,
          "bTriggerOnFollower": false,
          "bForceTriggerOnState": false,
          "TrackIndex": 3,
          "LinkedMontage": {
            "ObjectName": "AnimMontage'AM_Skill01_Start'",
            "ObjectPath": "Client/Content/Aki/Character/Role/FemaleXL/ChangLi/CommonAnim/AM_Skill01_Start.0"
          },
          "SlotIndex": 0,
          "SegmentIndex": 0,
          "LinkMethod": "EAnimLinkMethod::Absolute",
          "CachedLinkMethod": "EAnimLinkMethod::Absolute",
          "SegmentBeginTime": 0.0,
          "SegmentLength": 1.1666666,
          "LinkValue": 0.7806547,
          "LinkedSequence": {
            "ObjectName": "AnimSequence'Skill01_Start'",
            "ObjectPath": "Client/Content/Aki/Character/Role/FemaleXL/ChangLi/CommonAnim/Skill01_Start.6"
          }
        },
        {
          "TriggerTimeOffset": 0.0,
          "EndTriggerTimeOffset": 0.0001,
          "TriggerWeightThreshold": 1E-05,
          "NotifyName": "TsAnimNotifyAddBuff_C",
          "Notify": {
            "ObjectName": "TsAnimNotifyAddBuff_C'AM_Skill01_Start:TsAnimNotifyAddBuff_C_1'",
            "ObjectPath": "Client/Content/Aki/Character/Role/FemaleXL/ChangLi/CommonAnim/AM_Skill01_Start.8"
          },
          "NotifyStateClass": null,
          "Duration": 0.0,
          "EndLink": {
            "LinkedMontage": null,
            "SlotIndex": 0,
            "SegmentIndex": -1,
            "LinkMethod": "EAnimLinkMethod::Absolute",
            "CachedLinkMethod": "EAnimLinkMethod::Absolute",
            "SegmentBeginTime": 0.0,
            "SegmentLength": 0.0,
            "LinkValue": 0.780655,
            "LinkedSequence": null
          },
          "bConvertedFromBranchingPoint": false,
          "MontageTickType": "EMontageNotifyTickType::Queued",
          "bEnabled": true,
          "NotifyTriggerChance": 1.0,
          "NotifyFilterType": "ENotifyFilterType::NoFiltering",
          "NotifyFilterLOD": 0,
          "bTriggerOnDedicatedServer": true,
          "bTriggerOnFollower": false,
          "bForceTriggerOnState": false,
          "TrackIndex": 4,
          "LinkedMontage": {
            "ObjectName": "AnimMontage'AM_Skill01_Start'",
            "ObjectPath": "Client/Content/Aki/Character/Role/FemaleXL/ChangLi/CommonAnim/AM_Skill01_Start.0"
          },
          "SlotIndex": 0,
          "SegmentIndex": 0,
          "LinkMethod": "EAnimLinkMethod::Absolute",
          "CachedLinkMethod": "EAnimLinkMethod::Absolute",
          "SegmentBeginTime": 0.0,
          "SegmentLength": 1.1666666,
          "LinkValue": 0.780655,
          "LinkedSequence": {
            "ObjectName": "AnimSequence'Skill01_Start'",
            "ObjectPath": "Client/Content/Aki/Character/Role/FemaleXL/ChangLi/CommonAnim/Skill01_Start.6"
          }
        },
        {
          "TriggerTimeOffset": 0.0,
          "EndTriggerTimeOffset": 0.0001,
          "TriggerWeightThreshold": 1E-05,
          "NotifyName": "TsAnimNotifyAddBuff_C",
          "Notify": {
            "ObjectName": "TsAnimNotifyAddBuff_C'AM_Skill01_Start:TsAnimNotifyAddBuff_C_2'",
            "ObjectPath": "Client/Content/Aki/Character/Role/FemaleXL/ChangLi/CommonAnim/AM_Skill01_Start.9"
          },
          "NotifyStateClass": null,
          "Duration": 0.0,
          "EndLink": {
            "LinkedMontage": null,
            "SlotIndex": 0,
            "SegmentIndex": -1,
            "LinkMethod": "EAnimLinkMethod::Absolute",
            "CachedLinkMethod": "EAnimLinkMethod::Absolute",
            "SegmentBeginTime": 0.0,
            "SegmentLength": 0.0,
            "LinkValue": 0.780655,
            "LinkedSequence": null
          },
          "bConvertedFromBranchingPoint": false,
          "MontageTickType": "EMontageNotifyTickType::Queued",
          "bEnabled": true,
          "NotifyTriggerChance": 1.0,
          "NotifyFilterType": "ENotifyFilterType::NoFiltering",
          "NotifyFilterLOD": 0,
          "bTriggerOnDedicatedServer": true,
          "bTriggerOnFollower": false,
          "bForceTriggerOnState": false,
          "TrackIndex": 5,
          "LinkedMontage": {
            "ObjectName": "AnimMontage'AM_Skill01_Start'",
            "ObjectPath": "Client/Content/Aki/Character/Role/FemaleXL/ChangLi/CommonAnim/AM_Skill01_Start.0"
          },
          "SlotIndex": 0,
          "SegmentIndex": 0,
          "LinkMethod": "EAnimLinkMethod::Absolute",
          "CachedLinkMethod": "EAnimLinkMethod::Absolute",
          "SegmentBeginTime": 0.0,
          "SegmentLength": 1.1666666,
          "LinkValue": 0.780655,
          "LinkedSequence": {
            "ObjectName": "AnimSequence'Skill01_Start'",
            "ObjectPath": "Client/Content/Aki/Character/Role/FemaleXL/ChangLi/CommonAnim/Skill01_Start.6"
          }
        },
        {
          "TriggerTimeOffset": 0.0,
          "EndTriggerTimeOffset": 0.0001,
          "TriggerWeightThreshold": 1E-05,
          "NotifyName": "TsAnimNotifyWeaponHide_C",
          "Notify": {
            "ObjectName": "TsAnimNotifyWeaponHide_C'AM_Skill01_Start:TsAnimNotifyWeaponHide_C_2'",
            "ObjectPath": "Client/Content/Aki/Character/Role/FemaleXL/ChangLi/CommonAnim/AM_Skill01_Start.22"
          },
          "NotifyStateClass": null,
          "Duration": 0.0,
          "EndLink": {
            "LinkedMontage": null,
            "SlotIndex": 0,
            "SegmentIndex": -1,
            "LinkMethod": "EAnimLinkMethod::Absolute",
            "CachedLinkMethod": "EAnimLinkMethod::Absolute",
            "SegmentBeginTime": 0.0,
            "SegmentLength": 0.0,
            "LinkValue": 0.0,
            "LinkedSequence": null
          },
          "bConvertedFromBranchingPoint": false,
          "MontageTickType": "EMontageNotifyTickType::Queued",
          "bEnabled": true,
          "NotifyTriggerChance": 1.0,
          "NotifyFilterType": "ENotifyFilterType::NoFiltering",
          "NotifyFilterLOD": 0,
          "bTriggerOnDedicatedServer": true,
          "bTriggerOnFollower": false,
          "bForceTriggerOnState": false,
          "TrackIndex": 6,
          "LinkedMontage": {
            "ObjectName": "AnimMontage'AM_Skill01_Start'",
            "ObjectPath": "Client/Content/Aki/Character/Role/FemaleXL/ChangLi/CommonAnim/AM_Skill01_Start.0"
          },
          "SlotIndex": 0,
          "SegmentIndex": 0,
          "LinkMethod": "EAnimLinkMethod::Absolute",
          "CachedLinkMethod": "EAnimLinkMethod::Absolute",
          "SegmentBeginTime": 0.0,
          "SegmentLength": 1.1666666,
          "LinkValue": 0.79647833,
          "LinkedSequence": {
            "ObjectName": "AnimSequence'Skill01_Start'",
            "ObjectPath": "Client/Content/Aki/Character/Role/FemaleXL/ChangLi/CommonAnim/Skill01_Start.6"
          }
        }
      ],
      "SequenceLength": 1.1666666,
      "Skeleton": {
        "ObjectName": "Skeleton'R2T1ChangLiMd10011_Skeleton'",
        "ObjectPath": "Client/Content/Aki/Character/Role/FemaleXL/ChangLi/R2T1ChangLiMd10011/Model/R2T1ChangLiMd10011_Skeleton.16"
      }
    },
    "SkeletonGuid": "00C14295-44D7D779-39150789-FBA09515"
  },
  {
    "Type": "AnimNotifyStateAddMaterialControllerDataGroup_C",
    "Name": "AnimNotifyStateAddMaterialControllerDataGroup_C_0",
    "Flags": "RF_Transactional | RF_WasLoaded | RF_LoadCompleted",
    "Class": "TypeScriptGeneratedClass'Client/Content/Aki/TypeScript/Game/Render/Character/AnimNotify/AnimNotifyStateAddMaterialControllerDataGroup.AnimNotifyStateAddMaterialControllerDataGroup_C'",
    "Outer": {
      "ObjectName": "AnimMontage'AM_Skill01_Start'",
      "ObjectPath": "Client/Content/Aki/Character/Role/FemaleXL/ChangLi/CommonAnim/AM_Skill01_Start.0"
    },
    "Template": {
      "ObjectName": "AnimNotifyStateAddMaterialControllerDataGroup_C'Default__AnimNotifyStateAddMaterialControllerDataGroup_C'",
      "ObjectPath": "Client/Content/Aki/TypeScript/Game/Render/Character/AnimNotify/AnimNotifyStateAddMaterialControllerDataGroup.4"
    },
    "Properties": {
      "MaterialAssetData": {
        "ObjectName": "PD_CharacterControllerDataGroup_C'DA_Fx_Group_FightDiss_End'",
        "ObjectPath": "Client/Content/Aki/Effect/MaterialController/DA_Character/Changli/DA_Fx_Group_FightDiss_End.0"
      },
      "exportIndex": 24
    }
  },
  {
    "Type": "AnimNotifyStateAddMaterialControllerDataGroup_C",
    "Name": "AnimNotifyStateAddMaterialControllerDataGroup_C_1",
    "Flags": "RF_Transactional | RF_WasLoaded | RF_LoadCompleted",
    "Class": "TypeScriptGeneratedClass'Client/Content/Aki/TypeScript/Game/Render/Character/AnimNotify/AnimNotifyStateAddMaterialControllerDataGroup.AnimNotifyStateAddMaterialControllerDataGroup_C'",
    "Outer": {
      "ObjectName": "AnimMontage'AM_Skill01_Start'",
      "ObjectPath": "Client/Content/Aki/Character/Role/FemaleXL/ChangLi/CommonAnim/AM_Skill01_Start.0"
    },
    "Template": {
      "ObjectName": "AnimNotifyStateAddMaterialControllerDataGroup_C'Default__AnimNotifyStateAddMaterialControllerDataGroup_C'",
      "ObjectPath": "Client/Content/Aki/TypeScript/Game/Render/Character/AnimNotify/AnimNotifyStateAddMaterialControllerDataGroup.4"
    },
    "Properties": {
      "MaterialAssetData": {
        "ObjectName": "PD_CharacterControllerDataGroup_C'DA_Fx_Group_FightDiss'",
        "ObjectPath": "Client/Content/Aki/Effect/MaterialController/DA_Character/Changli/DA_Fx_Group_FightDiss.0"
      },
      "exportIndex": 9
    }
  },
  {
    "Type": "AnimNotifyStateGhost_C",
    "Name": "AnimNotifyStateGhost_C_0",
    "Flags": "RF_Transactional | RF_WasLoaded | RF_LoadCompleted",
    "Class": "TypeScriptGeneratedClass'Client/Content/Aki/TypeScript/Game/Render/Effect/AnimNotify/AnimNotifyStateGhost.AnimNotifyStateGhost_C'",
    "Outer": {
      "ObjectName": "AnimMontage'AM_Skill01_Start'",
      "ObjectPath": "Client/Content/Aki/Character/Role/FemaleXL/ChangLi/CommonAnim/AM_Skill01_Start.0"
    },
    "Template": {
      "ObjectName": "AnimNotifyStateGhost_C'Default__AnimNotifyStateGhost_C'",
      "ObjectPath": "Client/Content/Aki/TypeScript/Game/Render/Effect/AnimNotify/AnimNotifyStateGhost.5"
    },
    "Properties": {
      "GhostLifeTime": 1.5,
      "EffectDataAssetRef": {
        "AssetPathName": "/Game/Aki/Effect/DataAsset/Ghost/DA_Fx_Ghost_R2T1Changli_140001.DA_Fx_Ghost_R2T1Changli_140001",
        "SubPathString": ""
      },
      "UseSpawnRate": false,
      "SpawnInterval": 1.0,
      "exportIndex": 10
    }
  },
  {
    "Type": "AnimNotifyStateGhost_C",
    "Name": "AnimNotifyStateGhost_C_1",
    "Flags": "RF_Transactional | RF_WasLoaded | RF_LoadCompleted",
    "Class": "TypeScriptGeneratedClass'Client/Content/Aki/TypeScript/Game/Render/Effect/AnimNotify/AnimNotifyStateGhost.AnimNotifyStateGhost_C'",
    "Outer": {
      "ObjectName": "AnimMontage'AM_Skill01_Start'",
      "ObjectPath": "Client/Content/Aki/Character/Role/FemaleXL/ChangLi/CommonAnim/AM_Skill01_Start.0"
    },
    "Template": {
      "ObjectName": "AnimNotifyStateGhost_C'Default__AnimNotifyStateGhost_C'",
      "ObjectPath": "Client/Content/Aki/TypeScript/Game/Render/Effect/AnimNotify/AnimNotifyStateGhost.5"
    },
    "Properties": {
      "SpawnRate": 10.0,
      "GhostLifeTime": 1.0,
      "EffectDataAssetRef": {
        "AssetPathName": "/Game/Aki/Effect/DataAsset/Ghost/DA_Fx_Ghost_R2T1Changli_140001.DA_Fx_Ghost_R2T1Changli_140001",
        "SubPathString": ""
      },
      "SpawnInterval": 0.0,
      "exportIndex": 20
    }
  },
  {
    "Type": "AnimNotifyStateGhost_C",
    "Name": "AnimNotifyStateGhost_C_2",
    "Flags": "RF_Transactional | RF_WasLoaded | RF_LoadCompleted",
    "Class": "TypeScriptGeneratedClass'Client/Content/Aki/TypeScript/Game/Render/Effect/AnimNotify/AnimNotifyStateGhost.AnimNotifyStateGhost_C'",
    "Outer": {
      "ObjectName": "AnimMontage'AM_Skill01_Start'",
      "ObjectPath": "Client/Content/Aki/Character/Role/FemaleXL/ChangLi/CommonAnim/AM_Skill01_Start.0"
    },
    "Template": {
      "ObjectName": "AnimNotifyStateGhost_C'Default__AnimNotifyStateGhost_C'",
      "ObjectPath": "Client/Content/Aki/TypeScript/Game/Render/Effect/AnimNotify/AnimNotifyStateGhost.5"
    },
    "Properties": {
      "GhostLifeTime": 1.0,
      "EffectDataAssetRef": {
        "AssetPathName": "/Game/Aki/Effect/DataAsset/Ghost/DA_Fx_Ghost_R2T1Changli_140001.DA_Fx_Ghost_R2T1Changli_140001",
        "SubPathString": ""
      },
      "UseSpawnRate": false,
      "SpawnInterval": 1.0,
      "exportIndex": 22
    }
  },
  {
    "Type": "AnimNotifyStateGhost_C",
    "Name": "AnimNotifyStateGhost_C_3",
    "Flags": "RF_Transactional | RF_WasLoaded | RF_LoadCompleted",
    "Class": "TypeScriptGeneratedClass'Client/Content/Aki/TypeScript/Game/Render/Effect/AnimNotify/AnimNotifyStateGhost.AnimNotifyStateGhost_C'",
    "Outer": {
      "ObjectName": "AnimMontage'AM_Skill01_Start'",
      "ObjectPath": "Client/Content/Aki/Character/Role/FemaleXL/ChangLi/CommonAnim/AM_Skill01_Start.0"
    },
    "Template": {
      "ObjectName": "AnimNotifyStateGhost_C'Default__AnimNotifyStateGhost_C'",
      "ObjectPath": "Client/Content/Aki/TypeScript/Game/Render/Effect/AnimNotify/AnimNotifyStateGhost.5"
    },
    "Properties": {
      "GhostLifeTime": 0.4,
      "EffectDataAssetRef": {
        "AssetPathName": "/Game/Aki/Effect/DataAsset/Ghost/DA_Fx_Ghost_R2T1Changli_140001.DA_Fx_Ghost_R2T1Changli_140001",
        "SubPathString": ""
      },
      "UseSpawnRate": false,
      "SpawnInterval": 0.1,
      "exportIndex": 23
    }
  },
  {
    "Type": "TsAnimNotifyAddBuff_C",
    "Name": "TsAnimNotifyAddBuff_C_0",
    "Flags": "RF_Transactional | RF_WasLoaded | RF_LoadCompleted",
    "Class": "TypeScriptGeneratedClass'Client/Content/Aki/TypeScript/Game/AnimNotify/TsAnimNotifyAddBuff.TsAnimNotifyAddBuff_C'",
    "Outer": {
      "ObjectName": "AnimMontage'AM_Skill01_Start'",
      "ObjectPath": "Client/Content/Aki/Character/Role/FemaleXL/ChangLi/CommonAnim/AM_Skill01_Start.0"
    },
    "Template": {
      "ObjectName": "TsAnimNotifyAddBuff_C'Default__TsAnimNotifyAddBuff_C'",
      "ObjectPath": "Client/Content/Aki/TypeScript/Game/AnimNotify/TsAnimNotifyAddBuff.3"
    },
    "Properties": {
      "BuffId": 1205000001,
      "exportIndex": 25
    }
  },
  {
    "Type": "TsAnimNotifyAddBuff_C",
    "Name": "TsAnimNotifyAddBuff_C_1",
    "Flags": "RF_Transactional | RF_WasLoaded | RF_LoadCompleted",
    "Class": "TypeScriptGeneratedClass'Client/Content/Aki/TypeScript/Game/AnimNotify/TsAnimNotifyAddBuff.TsAnimNotifyAddBuff_C'",
    "Outer": {
      "ObjectName": "AnimMontage'AM_Skill01_Start'",
      "ObjectPath": "Client/Content/Aki/Character/Role/FemaleXL/ChangLi/CommonAnim/AM_Skill01_Start.0"
    },
    "Template": {
      "ObjectName": "TsAnimNotifyAddBuff_C'Default__TsAnimNotifyAddBuff_C'",
      "ObjectPath": "Client/Content/Aki/TypeScript/Game/AnimNotify/TsAnimNotifyAddBuff.3"
    },
    "Properties": {
      "BuffId": 1205000012,
      "exportIndex": 25
    }
  },
  {
    "Type": "TsAnimNotifyAddBuff_C",
    "Name": "TsAnimNotifyAddBuff_C_2",
    "Flags": "RF_Transactional | RF_WasLoaded | RF_LoadCompleted",
    "Class": "TypeScriptGeneratedClass'Client/Content/Aki/TypeScript/Game/AnimNotify/TsAnimNotifyAddBuff.TsAnimNotifyAddBuff_C'",
    "Outer": {
      "ObjectName": "AnimMontage'AM_Skill01_Start'",
      "ObjectPath": "Client/Content/Aki/Character/Role/FemaleXL/ChangLi/CommonAnim/AM_Skill01_Start.0"
    },
    "Template": {
      "ObjectName": "TsAnimNotifyAddBuff_C'Default__TsAnimNotifyAddBuff_C'",
      "ObjectPath": "Client/Content/Aki/TypeScript/Game/AnimNotify/TsAnimNotifyAddBuff.3"
    },
    "Properties": {
      "BuffId": 1205000011,
      "exportIndex": 25
    }
  },
  {
    "Type": "TsAnimNotifyAudioEvent_C",
    "Name": "TsAnimNotifyAudioEvent_C_0",
    "Flags": "RF_Transactional | RF_WasLoaded | RF_LoadCompleted",
    "Class": "TypeScriptGeneratedClass'Client/Content/Aki/TypeScript/Game/AnimNotify/TsAnimNotifyAudioEvent.TsAnimNotifyAudioEvent_C'",
    "Outer": {
      "ObjectName": "AnimMontage'AM_Skill01_Start'",
      "ObjectPath": "Client/Content/Aki/Character/Role/FemaleXL/ChangLi/CommonAnim/AM_Skill01_Start.0"
    },
    "Template": {
      "ObjectName": "TsAnimNotifyAudioEvent_C'Default__TsAnimNotifyAudioEvent_C'",
      "ObjectPath": "Client/Content/Aki/TypeScript/Game/AnimNotify/TsAnimNotifyAudioEvent.3"
    },
    "Properties": {
      "AudioEvent": {
        "AssetPathName": "/Game/Aki/WwiseAudio/Events/play_vo_changli_bat_skill.play_vo_changli_bat_skill",
        "SubPathString": ""
      },
      "exportIndex": 18
    }
  },
  {
    "Type": "TsAnimNotifyCameraModify_C",
    "Name": "TsAnimNotifyCameraModify_C_0",
    "Flags": "RF_Transactional | RF_WasLoaded | RF_LoadCompleted",
    "Class": "TypeScriptGeneratedClass'Client/Content/Aki/TypeScript/Game/AnimNotify/TsAnimNotifyCameraModify.TsAnimNotifyCameraModify_C'",
    "Outer": {
      "ObjectName": "AnimMontage'AM_Skill01_Start'",
      "ObjectPath": "Client/Content/Aki/Character/Role/FemaleXL/ChangLi/CommonAnim/AM_Skill01_Start.0"
    },
    "Template": {
      "ObjectName": "TsAnimNotifyCameraModify_C'Default__TsAnimNotifyCameraModify_C'",
      "ObjectPath": "Client/Content/Aki/TypeScript/Game/AnimNotify/TsAnimNotifyCameraModify.3"
    },
    "Properties": {
      "持续时间": 1.0,
      "淡入时间": 0.2,
      "淡出时间": 0.3,
      "打断淡出时间": 0.3,
      "相机修改配置": {
        "Priority_101_E74404724F7BCD1A815B9E8ECCEE64EC": 90,
        "IsModifiedArmLength_73_1686AE5842DD198072484BB2D855CAEB": true,
        "ArmLength_74_192752C04380D5CAF2EB7E910DC5C9C5": 700.0,
        "IsModifiedArmRotationPitch_94_6C16441D44C806A072B75DA882811D0C": true,
        "IsModifiedArmRotationYaw_95_FBE820DB4C8D5B75CEF242854F6F3774": true,
        "ArmRotation_77_B66F0D944DE7F4829886B997E0B1B89F": {
          "Pitch": -5.0,
          "Yaw": 0.0,
          "Roll": 0.0
        },
        "OverrideCameraInput_59_0083E3164D765950CF70528078BF8218": true,
        "ResetFinalArmRotation_70_56DCE7204671EC361892799BE39735C5": false,
        "IsLockInput_86_CDDE4FA4418F23E40016969CB0D3623C": true
      },
      "exportIndex": 19
    }
  },
  {
    "Type": "TsAnimNotifyChangeSkillPriority_C",
    "Name": "TsAnimNotifyChangeSkillPriority_C_0",
    "Flags": "RF_Transactional | RF_WasLoaded | RF_LoadCompleted",
    "Class": "TypeScriptGeneratedClass'Client/Content/Aki/TypeScript/Game/AnimNotify/TsAnimNotifyChangeSkillPriority.TsAnimNotifyChangeSkillPriority_C'",
    "Outer": {
      "ObjectName": "AnimMontage'AM_Skill01_Start'",
      "ObjectPath": "Client/Content/Aki/Character/Role/FemaleXL/ChangLi/CommonAnim/AM_Skill01_Start.0"
    },
    "Template": {
      "ObjectName": "TsAnimNotifyChangeSkillPriority_C'Default__TsAnimNotifyChangeSkillPriority_C'",
      "ObjectPath": "Client/Content/Aki/TypeScript/Game/AnimNotify/TsAnimNotifyChangeSkillPriority.3"
    },
    "Properties": {
      "Priority": 7.0,
      "exportIndex": 12
    }
  },
  {
    "Type": "TsAnimNotifyReSkillEvent_C",
    "Name": "TsAnimNotifyReSkillEvent_C_0",
    "Flags": "RF_Transactional | RF_WasLoaded | RF_LoadCompleted",
    "Class": "TypeScriptGeneratedClass'Client/Content/Aki/TypeScript/Game/AnimNotify/TsAnimNotifyReSkillEvent.TsAnimNotifyReSkillEvent_C'",
    "Outer": {
      "ObjectName": "AnimMontage'AM_Skill01_Start'",
      "ObjectPath": "Client/Content/Aki/Character/Role/FemaleXL/ChangLi/CommonAnim/AM_Skill01_Start.0"
    },
    "Template": {
      "ObjectName": "TsAnimNotifyReSkillEvent_C'Default__TsAnimNotifyReSkillEvent_C'",
      "ObjectPath": "Client/Content/Aki/TypeScript/Game/AnimNotify/TsAnimNotifyReSkillEvent.3"
    },
    "Properties": {
      "子弹数据名": "1205201001",
      "exportIndex": 21
    }
  },
  {
    "Type": "TsAnimNotifyStateAddBuff_C",
    "Name": "TsAnimNotifyStateAddBuff_C_0",
    "Flags": "RF_Transactional | RF_WasLoaded | RF_LoadCompleted",
    "Class": "TypeScriptGeneratedClass'Client/Content/Aki/TypeScript/Game/AnimNotifyState/TsAnimNotifyStateAddBuff.TsAnimNotifyStateAddBuff_C'",
    "Outer": {
      "ObjectName": "AnimMontage'AM_Skill01_Start'",
      "ObjectPath": "Client/Content/Aki/Character/Role/FemaleXL/ChangLi/CommonAnim/AM_Skill01_Start.0"
    },
    "Template": {
      "ObjectName": "TsAnimNotifyStateAddBuff_C'Default__TsAnimNotifyStateAddBuff_C'",
      "ObjectPath": "Client/Content/Aki/TypeScript/Game/AnimNotifyState/TsAnimNotifyStateAddBuff.4"
    },
    "Properties": {
      "BuffId": 1205900101,
      "exportIndex": 16
    }
  },
  {
    "Type": "TsAnimNotifyStateAddBuff_C",
    "Name": "TsAnimNotifyStateAddBuff_C_1",
    "Flags": "RF_Transactional | RF_WasLoaded | RF_LoadCompleted",
    "Class": "TypeScriptGeneratedClass'Client/Content/Aki/TypeScript/Game/AnimNotifyState/TsAnimNotifyStateAddBuff.TsAnimNotifyStateAddBuff_C'",
    "Outer": {
      "ObjectName": "AnimMontage'AM_Skill01_Start'",
      "ObjectPath": "Client/Content/Aki/Character/Role/FemaleXL/ChangLi/CommonAnim/AM_Skill01_Start.0"
    },
    "Template": {
      "ObjectName": "TsAnimNotifyStateAddBuff_C'Default__TsAnimNotifyStateAddBuff_C'",
      "ObjectPath": "Client/Content/Aki/TypeScript/Game/AnimNotifyState/TsAnimNotifyStateAddBuff.4"
    },
    "Properties": {
      "BuffId": 1205900102,
      "exportIndex": 17
    }
  },
  {
    "Type": "TsAnimNotifyStateAddTag_C",
    "Name": "TsAnimNotifyStateAddTag_C_0",
    "Flags": "RF_Transactional | RF_WasLoaded | RF_LoadCompleted",
    "Class": "TypeScriptGeneratedClass'Client/Content/Aki/TypeScript/Game/AnimNotifyState/TsAnimNotifyStateAddTag.TsAnimNotifyStateAddTag_C'",
    "Outer": {
      "ObjectName": "AnimMontage'AM_Skill01_Start'",
      "ObjectPath": "Client/Content/Aki/Character/Role/FemaleXL/ChangLi/CommonAnim/AM_Skill01_Start.0"
    },
    "Template": {
      "ObjectName": "TsAnimNotifyStateAddTag_C'Default__TsAnimNotifyStateAddTag_C'",
      "ObjectPath": "Client/Content/Aki/TypeScript/Game/AnimNotifyState/TsAnimNotifyStateAddTag.4"
    },
    "Properties": {
      "Tag": {
        "TagName": "角色.R2T1ChangLiMd10011.buff相关.脱眼罩ing"
      },
      "exportIndex": 7
    }
  },
  {
    "Type": "TsAnimNotifyStateAddTag_C",
    "Name": "TsAnimNotifyStateAddTag_C_1",
    "Flags": "RF_Transactional | RF_WasLoaded | RF_LoadCompleted",
    "Class": "TypeScriptGeneratedClass'Client/Content/Aki/TypeScript/Game/AnimNotifyState/TsAnimNotifyStateAddTag.TsAnimNotifyStateAddTag_C'",
    "Outer": {
      "ObjectName": "AnimMontage'AM_Skill01_Start'",
      "ObjectPath": "Client/Content/Aki/Character/Role/FemaleXL/ChangLi/CommonAnim/AM_Skill01_Start.0"
    },
    "Template": {
      "ObjectName": "TsAnimNotifyStateAddTag_C'Default__TsAnimNotifyStateAddTag_C'",
      "ObjectPath": "Client/Content/Aki/TypeScript/Game/AnimNotifyState/TsAnimNotifyStateAddTag.4"
    },
    "Properties": {
      "Tag": {
        "TagName": "角色.BaseRole.状态通用标识.葫芦.葫芦隐藏"
      },
      "exportIndex": 13
    }
  },
  {
    "Type": "TsAnimNotifyStateAddTag_C",
    "Name": "TsAnimNotifyStateAddTag_C_2",
    "Flags": "RF_Transactional | RF_WasLoaded | RF_LoadCompleted",
    "Class": "TypeScriptGeneratedClass'Client/Content/Aki/TypeScript/Game/AnimNotifyState/TsAnimNotifyStateAddTag.TsAnimNotifyStateAddTag_C'",
    "Outer": {
      "ObjectName": "AnimMontage'AM_Skill01_Start'",
      "ObjectPath": "Client/Content/Aki/Character/Role/FemaleXL/ChangLi/CommonAnim/AM_Skill01_Start.0"
    },
    "Template": {
      "ObjectName": "TsAnimNotifyStateAddTag_C'Default__TsAnimNotifyStateAddTag_C'",
      "ObjectPath": "Client/Content/Aki/TypeScript/Game/AnimNotifyState/TsAnimNotifyStateAddTag.4"
    },
    "Properties": {
      "Tag": {
        "TagName": "角色.Common.切人不隐藏"
      },
      "exportIndex": 11
    }
  },
  {
    "Type": "TsAnimNotifyStateGoThrough_C",
    "Name": "TsAnimNotifyStateGoThrough_C_0",
    "Flags": "RF_Transactional | RF_WasLoaded | RF_LoadCompleted",
    "Class": "TypeScriptGeneratedClass'Client/Content/Aki/TypeScript/Game/AnimNotifyState/TsAnimNotifyStateGoThrough.TsAnimNotifyStateGoThrough_C'",
    "Outer": {
      "ObjectName": "AnimMontage'AM_Skill01_Start'",
      "ObjectPath": "Client/Content/Aki/Character/Role/FemaleXL/ChangLi/CommonAnim/AM_Skill01_Start.0"
    },
    "Template": {
      "ObjectName": "TsAnimNotifyStateGoThrough_C'Default__TsAnimNotifyStateGoThrough_C'",
      "ObjectPath": "Client/Content/Aki/TypeScript/Game/AnimNotifyState/TsAnimNotifyStateGoThrough.5"
    },
    "Properties": {
      "FirstGoThroughPriority": 31,
      "OldGoThroughPriority": 50.0,
      "OldHitPriority": 50.0,
      "LeftTime": -0.004269842,
      "IsEnd": true,
      "exportIndex": 8
    }
  },
  {
    "Type": "TsAnimNotifyStatePositionBranchTarget_C",
    "Name": "TsAnimNotifyStatePositionBranchTarget_C_1",
    "Flags": "RF_Transactional | RF_WasLoaded | RF_LoadCompleted",
    "Class": "TypeScriptGeneratedClass'Client/Content/Aki/TypeScript/Game/AnimNotifyState/TsAnimNotifyStatePositionBranchTarget.TsAnimNotifyStatePositionBranchTarget_C'",
    "Outer": {
      "ObjectName": "AnimMontage'AM_Skill01_Start'",
      "ObjectPath": "Client/Content/Aki/Character/Role/FemaleXL/ChangLi/CommonAnim/AM_Skill01_Start.0"
    },
    "Template": {
      "ObjectName": "TsAnimNotifyStatePositionBranchTarget_C'Default__TsAnimNotifyStatePositionBranchTarget_C'",
      "ObjectPath": "Client/Content/Aki/TypeScript/Game/AnimNotifyState/TsAnimNotifyStatePositionBranchTarget.6"
    },
    "Properties": {
      "Distance": 100.0,
      "MaxSpeed": 6000.0,
      "exportIndex": 14
    }
  },
  {
    "Type": "TsAnimNotifyWeaponHide_C",
    "Name": "TsAnimNotifyWeaponHide_C_1",
    "Flags": "RF_Transactional | RF_WasLoaded | RF_LoadCompleted",
    "Class": "TypeScriptGeneratedClass'Client/Content/Aki/TypeScript/Game/AnimNotify/TsAnimNotifyWeaponHide.TsAnimNotifyWeaponHide_C'",
    "Outer": {
      "ObjectName": "AnimMontage'AM_Skill01_Start'",
      "ObjectPath": "Client/Content/Aki/Character/Role/FemaleXL/ChangLi/CommonAnim/AM_Skill01_Start.0"
    },
    "Template": {
      "ObjectName": "TsAnimNotifyWeaponHide_C'Default__TsAnimNotifyWeaponHide_C'",
      "ObjectPath": "Client/Content/Aki/TypeScript/Game/AnimNotify/TsAnimNotifyWeaponHide.3"
    },
    "Properties": {
      "exportIndex": 15
    }
  },
  {
    "Type": "TsAnimNotifyWeaponHide_C",
    "Name": "TsAnimNotifyWeaponHide_C_2",
    "Flags": "RF_Transactional | RF_WasLoaded | RF_LoadCompleted",
    "Class": "TypeScriptGeneratedClass'Client/Content/Aki/TypeScript/Game/AnimNotify/TsAnimNotifyWeaponHide.TsAnimNotifyWeaponHide_C'",
    "Outer": {
      "ObjectName": "AnimMontage'AM_Skill01_Start'",
      "ObjectPath": "Client/Content/Aki/Character/Role/FemaleXL/ChangLi/CommonAnim/AM_Skill01_Start.0"
    },
    "Template": {
      "ObjectName": "TsAnimNotifyWeaponHide_C'Default__TsAnimNotifyWeaponHide_C'",
      "ObjectPath": "Client/Content/Aki/TypeScript/Game/AnimNotify/TsAnimNotifyWeaponHide.3"
    },
    "Properties": {
      "Hide": false,
      "WeaponIndex": 0,
      "HideEffect": false,
      "exportIndex": 26
    }
  }
]